.flake8
.gitignore
.gitmodules
.isort.cfg
.pre-commit-config.yaml
BUILD_TIMELORD.md
CHANGELOG.md
CODE_OF_CONDUCT.md
CONTRIBUTING.md
INSTALL.md
Install-gui.ps1
Install.ps1
LICENSE
README.md
azure-pipelines.yml
install-gui.sh
install-timelord.sh
install.sh
installhelper.py
mypy.ini
pyproject.toml
run-py-tests.sh
setup.py
.github/ISSUE_TEMPLATE/bug_report.md
.github/ISSUE_TEMPLATE/config.yml
.github/linters/.flake8
.github/linters/.isort.cfg
.github/linters/.markdown-lint.yml
.github/linters/.python-black
.github/linters/.python-lint
.github/workflows/build-linux-arm64-installer.yml
.github/workflows/build-linux-installer-deb.yml
.github/workflows/build-linux-installer-rpm.yml
.github/workflows/build-macos-installer.yml
.github/workflows/build-windows-installer.yml
benchmarks/coin_store.py
build_scripts/build_linux_deb.sh
build_scripts/build_linux_rpm.sh
build_scripts/build_macos.sh
build_scripts/build_macos_m1.sh
build_scripts/build_windows.ps1
build_scripts/clean-runner.sh
build_scripts/installer-version.py
mozilla-ca/.gitignore
mozilla-ca/LICENSE
mozilla-ca/__init__.py
mozilla-ca/cacert.pem
mozilla-ca/.github/workflows/update-cert.yaml
stor/__init__.py
stor/py.typed
stor/pyinstaller.spec
stor-blockchain-gui/.editorconfig
stor-blockchain-gui/.env
stor-blockchain-gui/.env.example
stor-blockchain-gui/.eslintignore
stor-blockchain-gui/.eslintrc.js
stor-blockchain-gui/.gitignore
stor-blockchain-gui/.linguirc
stor-blockchain-gui/.prettierrc.js
stor-blockchain-gui/CODE_OF_CONDUCT.md
stor-blockchain-gui/CONTRIBUTING.md
stor-blockchain-gui/LICENSE
stor-blockchain-gui/README.md
stor-blockchain-gui/babel.config.js
stor-blockchain-gui/crowdin.yml
stor-blockchain-gui/entitlements.mac.plist
stor-blockchain-gui/package-lock.json
stor-blockchain-gui/package.json
stor-blockchain-gui/remote.md
stor-blockchain-gui/storblockchain.provisionprofile
stor-blockchain-gui/tsconfig.json
stor-blockchain-gui/webpack.electron.babel.ts
stor-blockchain-gui/webpack.react.babel.ts
stor_blockchain.egg-info/PKG-INFO
stor_blockchain.egg-info/SOURCES.txt
stor_blockchain.egg-info/dependency_links.txt
stor_blockchain.egg-info/entry_points.txt
stor_blockchain.egg-info/not-zip-safe
stor_blockchain.egg-info/requires.txt
stor_blockchain.egg-info/top_level.txt
