Metadata-Version: 2.1
Name: stor-blockchain
Version: 1.0.4
Summary: Stor blockchain full node, farmer, timelord, and wallet.
Home-page: https://stor.network/
Author: Stor Network
Author-email: info@stor.network
License: Apache License
Keywords: stor blockchain node
Platform: UNKNOWN
Requires-Python: >=3.7, <4
Provides-Extra: dev
Provides-Extra: upnp
Provides-Extra: uvloop
